{
  "displayName": "S3 浏览器",
  "description": "在 VS Code 中浏览和管理任意 S3 兼容的对象存储",
  "viewContainerTitle": "S3",
  "viewName": "S3 浏览器",
  "cmd.addConnection": "添加 S3 连接...",
  "cmd.refresh": "刷新",
  "cmd.uploadFile": "上传文件...",
  "cmd.downloadFile": "下载...",
  "cmd.delete": "删除",
  "cmd.editConnection": "编辑连接...",
  "cmd.removeConnection": "移除连接",
  "cmd.copyPath": "复制路径",
  "cmd.previewFile": "预览文件",
  "cmd.rename": "重命名...",
  "cmd.newFolder": "新建文件夹...",
  "cmd.searchFiles": "搜索文件...",
  "cmd.goToPath": "跳转到路径...",
  "cmd.getInfo": "详细信息",
  "cmd.jumpHistory": "跳转历史...",
  "cmd.openConnection": "打开连接"
}